cyberpanel_cf_dns/__init__.py
cyberpanel_cf_dns/__main__.py
cyberpanel_cf_dns/main.py
cyberpanel_cf_dns-0.1.0.dist-info/METADATA
cyberpanel_cf_dns-0.1.0.dist-info/WHEEL
cyberpanel_cf_dns-0.1.0.dist-info/RECORD
